sinapsis_anthropic/helpers/__init__.py
sinapsis_anthropic/helpers/anthropic_keys.py
sinapsis_anthropic/helpers/env_var_keys.py
sinapsis_anthropic/helpers/mcp_tool_helper.py
sinapsis_anthropic/templates/__init__.py
sinapsis_anthropic/templates/anthropic_mcp.py
sinapsis_anthropic/templates/anthropic_multimodal.py
sinapsis_anthropic/templates/anthropic_text_generation.py
sinapsis_anthropic-0.1.5.dist-info/licenses/LICENSE
sinapsis_anthropic-0.1.5.dist-info/METADATA
sinapsis_anthropic-0.1.5.dist-info/WHEEL
sinapsis_anthropic-0.1.5.dist-info/top_level.txt
sinapsis_anthropic-0.1.5.dist-info/RECORD
