Metadata-Version: 2.4
Name: sinapsis-anthropic
Version: 0.1.5
Summary: Package with templates for AI-driven chatbots using Anthropic's Claude models
Author-email: SinapsisAI <dev@sinapsis.tech>
Project-URL: Homepage, https://sinapsis.tech
Project-URL: Documentation, https://docs.sinapsis.tech/docs
Project-URL: Tutorials, https://docs.sinapsis.tech/tutorials
Project-URL: Repository, https://github.com/Sinapsis-AI/sinapsis-chatbots.git
Requires-Python: >=3.10
License-File: LICENSE
Requires-Dist: anthropic>=0.51.0
Requires-Dist: sinapsis>=0.2.10
Requires-Dist: sinapsis-chatbots-base
Requires-Dist: sinapsis-generic-data-tools[pillow]>=0.1.10
Provides-Extra: chatbot
Requires-Dist: sinapsis-chatbots-base[chatbot]>=0.1.8; extra == "chatbot"
Provides-Extra: all
Requires-Dist: sinapsis-anthropic[chatbot]; extra == "all"
Dynamic: license-file
